[
    {
        "title":"Knitted jumper in maroon",
        "username":"jumperlover91",
        "image":"https://m.media-amazon.com/images/I/91F0TNvmWGL._AC_UL1500_.jpg"    
    },
    {
        "title":"Bluebell sundress",
        "username":"Summerchild",
        "image":"https://sheinsz.ltwebstatic.com/she_dist/images/bg-grey-ba96515e9b.png"    
    },
    {
        "title":"Orange Hat",
        "username":"Ilovehats",
        "image":"https://files.ekmcdn.com/bisoux123/images/pom-peace-of-mind-fine-knit-beanie-hat-with-wide-ribbed-turn-up-in-orange-18042-p.jpg?v=D5B47AEE-D021-4F94-B0CF-FF0307FD2B02"    
    },
    {
        "title":"",
        "username":"",
        "image":""    
    }
]